LICENSE
MANIFEST.in
README.rst
setup.py
luna/__init__.py
luna/projects.py
luna/run.py
luna/version.py
luna.egg-info/PKG-INFO
luna.egg-info/SOURCES.txt
luna.egg-info/dependency_links.txt
luna.egg-info/entry_points.txt
luna.egg-info/requires.txt
luna.egg-info/top_level.txt
luna/align/__init__.py
luna/align/tmalign.py
luna/analysis/__init__.py
luna/analysis/residues.py
luna/analysis/summary.py
luna/config/__init__.py
luna/config/default.cfg
luna/config/params.py
luna/data/BaseFeatures.fdef
luna/data/BaseFeatures_DIP2_NoMicrospecies.fdef
luna/data/LUNA.fdef
luna/data/MinimalFeatures.fdef
luna/data/ligand_expo.tsv
luna/data/precomputed_residue_atom_features.json
luna/data/precomputed_residue_data.json
luna/data/.ipynb_checkpoints/Untitled-checkpoint.ipynb
luna/docking/__init__.py
luna/docking/dock6/__init__.py
luna/docking/dock6/default.cfg
luna/docking/dock6/ligands.py
luna/docking/dock6/params.py
luna/interaction/__init__.py
luna/interaction/bind.cfg
luna/interaction/calc.py
luna/interaction/config.cfg
luna/interaction/config.py
luna/interaction/contact.py
luna/interaction/cov.py
luna/interaction/filter.cfg
luna/interaction/filter.py
luna/interaction/type.py
luna/interaction/view.py
luna/interaction/fp/__init__.py
luna/interaction/fp/fingerprint.py
luna/interaction/fp/shell.py
luna/interaction/fp/type.py
luna/interaction/fp/view.py
luna/mol/__init__.py
luna/mol/atom.py
luna/mol/charge_model.py
luna/mol/clustering.py
luna/mol/depiction.py
luna/mol/entry.py
luna/mol/features.py
luna/mol/fingerprint.py
luna/mol/groups.py
luna/mol/precomp_data.py
luna/mol/standardiser.py
luna/mol/templates.py
luna/mol/validator.py
luna/pdb/__init__.py
luna/pdb/builder.py
luna/pdb/convert.py
luna/pdb/core/__init__.py
luna/pdb/core/atom.py
luna/pdb/core/chain.py
luna/pdb/core/entity.py
luna/pdb/core/model.py
luna/pdb/core/residue.py
luna/pdb/core/structure.py
luna/pdb/io/__init__.py
luna/pdb/io/base.py
luna/pdb/io/extractor.py
luna/pdb/io/helpers.py
luna/pdb/io/selector.py
luna/pdb/neighbors/__init__.py
luna/pdb/neighbors/atom_group.py
luna/pdb/neighbors/residue.py
luna/pdb/parser/__init__.py
luna/pdb/parser/base.py
luna/pdb/parser/ftmap.py
