Metadata-Version: 2.1
Name: luna
Version: 0.14.0
Summary: LUNA: drug discovery toolkit
Home-page: https://github.com/keiserlab/LUNA
Download-URL: https://github.com/keiserlab/LUNA/tarball/v0.14.0
Author: Alexandre Fassio
Author-email: afassio@keiserlab.org
License: MIT
Project-URL: Bug Reports, https://github.com/keiserlab/LUNA/issues
Project-URL: Source, https://github.com/keiserlab/LUNA/
Keywords: luna eifp fifp hifp ifp interaction fingerprint protein-ligand molecule docking
Platform: UNKNOWN
Classifier: Programming Language :: Python
Classifier: Programming Language :: Python :: 3.7
Classifier: Programming Language :: Python :: 3.8
Classifier: Programming Language :: Python :: 3.9
Classifier: Programming Language :: Python :: 3.10
Classifier: Programming Language :: Python :: 3.11
Classifier: License :: OSI Approved :: MIT License
Classifier: Operating System :: OS Independent
Classifier: Development Status :: 4 - Beta
Classifier: Intended Audience :: Science/Research
Classifier: Intended Audience :: Developers
Classifier: Intended Audience :: End Users/Desktop
Classifier: Topic :: Scientific/Engineering :: Bio-Informatics
Classifier: Topic :: Scientific/Engineering :: Chemistry
Classifier: Topic :: Software Development :: Libraries :: Python Modules
Requires-Python: >=3.7, <4
Provides-Extra: docs
License-File: LICENSE
